interfusion/__init__.py
interfusion/config.py
interfusion/data_utils.py
interfusion/inference.py
interfusion/models.py
interfusion/trainer.py
interfusion_encoder-3.1.dist-info/METADATA
interfusion_encoder-3.1.dist-info/WHEEL
interfusion_encoder-3.1.dist-info/top_level.txt
interfusion_encoder-3.1.dist-info/RECORD
