Metadata-Version: 2.1
Name: interfusion-encoder
Version: 3.1
Summary: A package for training and inference of the InterFusion Encoder model
Home-page: UNKNOWN
Author: Edward Liu
Author-email: edwardliu01@gmail.com
License: UNKNOWN
Platform: UNKNOWN
Requires-Python: >=3.6
Requires-Dist: numpy
Requires-Dist: pandas
Requires-Dist: torch (>=1.7.0)
Requires-Dist: tqdm
Requires-Dist: transformers (>=4.0.0)
Requires-Dist: wandb
